{
  "recommended_slides": 22,
  "section_distribution": {
    "Introduction": 3,
    "Background": 3,
    "Methodology": 4,
    "Results": 5,
    "Discussion": 4,
    "Applications in Sports Engineering": 2,
    "Future Directions": 1
  },
  "ppt_outline": [
    {
      "name": "Introduction",
      "allocated_slides": 3,
      "slides": [
        {
          "title": "Overview of Sports Engineering Biomechanics",
          "points": [
            "Definition of Sports Engineering Biomechanics",
            "Importance in Athletic Performance",
            "Interdisciplinary Nature of the Field"
          ],
          "codes": [],
          "detail": "",
          "enriched_points": ""
        },
        {
          "title": "Objectives of the Report",
          "points": [
            "Explore fundamentals of biomechanics",
            "Discuss applications in sports",
            "Highlight case studies and future directions"
          ],
          "codes": [],
          "detail": "",
          "enriched_points": ""
        },
        {
          "title": "Significance of Biomechanics in Sports",
          "points": [
            "Enhances performance",
            "Improves safety",
            "Informs training techniques",
            "Optimizes equipment design"
          ],
          "codes": [],
          "detail": "",
          "enriched_points": ""
        }
      ]
    },
    {
      "name": "Background",
      "allocated_slides": 3,
      "slides": [
        {
          "title": "Fundamentals of Biomechanics",
          "points": [
            "Kinematics and Kinetics",
            "Forces and Motion",
            "Newton's Laws of Motion"
          ],
          "codes": [],
          "detail": "",
          "enriched_points": ""
        },
        {
          "title": "Role of Biomechanics in Sports",
          "points": [
            "Technique refinement",
            "Injury prevention",
            "Equipment optimization"
          ],
          "codes": [],
          "detail": "",
          "enriched_points": ""
        },
        {
          "title": "Historical Context",
          "points": [
            "Evolution of sports biomechanics",
            "Key milestones in research",
            "Impact on modern sports"
          ],
          "codes": [],
          "detail": "",
          "enriched_points": ""
        }
      ]
    },
    {
      "name": "Methodology",
      "allocated_slides": 4,
      "slides": [
        {
          "title": "Research Approach",
          "points": [
            "Literature review",
            "Case study analysis",
            "Interviews with experts"
          ],
          "codes": [],
          "detail": "",
          "enriched_points": ""
        },
        {
          "title": "Data Collection Techniques",
          "points": [
            "Motion analysis",
            "Wearable technology",
            "Biomechanical modeling"
          ],
          "codes": [],
          "detail": "",
          "enriched_points": ""
        },
        {
          "title": "Analysis Methods",
          "points": [
            "Statistical analysis",
            "Comparative studies",
            "Simulation techniques"
          ],
          "codes": [],
          "detail": "",
          "enriched_points": ""
        },
        {
          "title": "Limitations of the Study",
          "points": [
            "Sample size constraints",
            "Variability in athlete performance",
            "Technological limitations"
          ],
          "codes": [],
          "detail": "",
          "enriched_points": ""
        }
      ]
    },
    {
      "name": "Results",
      "allocated_slides": 5,
      "slides": [
        {
          "title": "Key Findings from Case Studies",
          "points": [
            "Improved performance metrics",
            "Injury reduction statistics",
            "Technique adjustments"
          ],
          "codes": [],
          "detail": "",
          "enriched_points": ""
        },
        {
          "title": "Impact of Biomechanics on Performance",
          "points": [
            "Quantitative improvements",
            "Qualitative feedback from athletes",
            "Longitudinal studies"
          ],
          "codes": [],
          "detail": "",
          "enriched_points": ""
        },
        {
          "title": "Equipment Design Innovations",
          "points": [
            "Advancements in materials",
            "Aerodynamic enhancements",
            "Safety features in gear"
          ],
          "codes": [],
          "detail": "",
          "enriched_points": ""
        },
        {
          "title": "Biomechanical Analysis Outcomes",
          "points": [
            "Data from motion capture",
            "Force application insights",
            "Asymmetry assessments"
          ],
          "codes": [],
          "detail": "",
          "enriched_points": ""
        },
        {
          "title": "Real-World Applications",
          "points": [
            "Success stories in various sports",
            "Collaboration between engineers and athletes",
            "Future potential in sports technology"
          ],
          "codes": [],
          "detail": "",
          "enriched_points": ""
        }
      ]
    },
    {
      "name": "Discussion",
      "allocated_slides": 4,
      "slides": [
        {
          "title": "Interplay Between Biomechanics and Engineering",
          "points": [
            "Synergy in performance enhancement",
            "Shared goals in athlete safety",
            "Innovative design processes"
          ],
          "codes": [],
          "detail": "",
          "enriched_points": ""
        },
        {
          "title": "Challenges in Implementation",
          "points": [
            "Cost of technology",
            "Accessibility for athletes",
            "Need for ongoing research"
          ],
          "codes": [],
          "detail": "",
          "enriched_points": ""
        },
        {
          "title": "Future Trends in Sports Biomechanics",
          "points": [
            "Integration of AI and machine learning",
            "Wearable technology advancements",
            "Personalized training programs"
          ],
          "codes": [],
          "detail": "",
          "enriched_points": ""
        },
        {
          "title": "Implications for Coaches and Athletes",
          "points": [
            "Adapting training methods",
            "Understanding biomechanics principles",
            "Utilizing technology for performance tracking"
          ],
          "codes": [],
          "detail": "",
          "enriched_points": ""
        }
      ]
    },
    {
      "name": "Applications in Sports Engineering",
      "allocated_slides": 2,
      "slides": [
        {
          "title": "Innovative Equipment Design",
          "points": [
            "Case studies of successful designs",
            "Material science advancements",
            "Aerodynamics in sports gear"
          ],
          "codes": [],
          "detail": "",
          "enriched_points": ""
        },
        {
          "title": "Real-World Impact on Athletes",
          "points": [
            "Performance improvements",
            "Injury prevention strategies",
            "Feedback from athletes and coaches"
          ],
          "codes": [],
          "detail": "",
          "enriched_points": ""
        }
      ]
    },
    {
      "name": "Future Directions",
      "allocated_slides": 1,
      "slides": [
        {
          "title": "Looking Ahead",
          "points": [
            "Continued research collaboration",
            "Emerging technologies in biomechanics",
            "Potential for new sports applications"
          ],
          "codes": [],
          "detail": "",
          "enriched_points": ""
        }
      ]
    }
  ]
}