{
  "recommended_slides": 22,
  "section_distribution": {
    "Introduction": 3,
    "Understanding Developmental Disorders": 4,
    "Current Interventions": 4,
    "Challenges in Interventions": 3,
    "Innovative Solutions": 4,
    "Case Studies": 2,
    "Future Directions": 2
  },
  "ppt_outline": [
    {
      "name": "Introduction",
      "allocated_slides": 3,
      "slides": [
        {
          "title": "Overview of Developmental Disorders",
          "points": [
            "Definition of developmental disorders",
            "Impact on learning and communication",
            "Importance of early intervention",
            "Statistics on prevalence",
            "Overview of intervention strategies"
          ],
          "codes": [],
          "detail": "",
          "enriched_points": ""
        },
        {
          "title": "Scope of the Presentation",
          "points": [
            "Types of developmental disorders",
            "Intervention strategies",
            "Evidence-based practices",
            "Challenges and solutions",
            "Future directions"
          ],
          "codes": [],
          "detail": "",
          "enriched_points": ""
        },
        {
          "title": "Objectives of the Report",
          "points": [
            "Highlight the need for effective interventions",
            "Explore various intervention strategies",
            "Discuss evidence-based practices",
            "Encourage collaboration among stakeholders"
          ],
          "codes": [],
          "detail": "",
          "enriched_points": ""
        }
      ]
    },
    {
      "name": "Understanding Developmental Disorders",
      "allocated_slides": 4,
      "slides": [
        {
          "title": "Types of Developmental Disorders",
          "points": [
            "Autism Spectrum Disorder (ASD)",
            "Intellectual disabilities (ID)",
            "Learning disabilities (LD)",
            "Prevalence rates and statistics",
            "Co-occurring conditions"
          ],
          "codes": [],
          "detail": "",
          "enriched_points": ""
        },
        {
          "title": "Characteristics of ASD",
          "points": [
            "Social interaction challenges",
            "Communication difficulties",
            "Repetitive behaviors",
            "Statistics on prevalence",
            "Gender differences in diagnosis"
          ],
          "codes": [],
          "detail": "",
          "enriched_points": ""
        },
        {
          "title": "Intellectual Disabilities Overview",
          "points": [
            "Definition and types",
            "Impact on cognitive functioning",
            "Prevalence in the population",
            "Common challenges faced",
            "Importance of support systems"
          ],
          "codes": [],
          "detail": "",
          "enriched_points": ""
        },
        {
          "title": "Learning Disabilities Explained",
          "points": [
            "Definition and types",
            "Impact on academic performance",
            "Prevalence rates",
            "Common signs and symptoms",
            "Need for tailored interventions"
          ],
          "codes": [],
          "detail": "",
          "enriched_points": ""
        }
      ]
    },
    {
      "name": "Current Interventions",
      "allocated_slides": 4,
      "slides": [
        {
          "title": "Behavioral Therapies",
          "points": [
            "Overview of behavioral therapies",
            "Applied Behavior Analysis (ABA)",
            "Effectiveness for ASD",
            "Early intensive treatment benefits",
            "Case studies and success stories"
          ],
          "codes": [],
          "detail": "",
          "enriched_points": ""
        },
        {
          "title": "Parent Training Programs",
          "points": [
            "Importance of parent involvement",
            "Strategies for effective communication",
            "Enhancing parent-child interactions",
            "Program examples",
            "Positive outcomes reported"
          ],
          "codes": [],
          "detail": "",
          "enriched_points": ""
        },
        {
          "title": "Educational Support Strategies",
          "points": [
            "Individualized Education Plans (IEPs)",
            "Tailored instruction methods",
            "Collaboration with educators",
            "Impact on academic growth",
            "Success stories"
          ],
          "codes": [],
          "detail": "",
          "enriched_points": ""
        },
        {
          "title": "Comprehensive Intervention Approaches",
          "points": [
            "Combining various strategies",
            "Holistic support for children",
            "Importance of early intervention",
            "Evidence of improved outcomes",
            "Collaborative models of care"
          ],
          "codes": [],
          "detail": "",
          "enriched_points": ""
        }
      ]
    },
    {
      "name": "Challenges in Interventions",
      "allocated_slides": 3,
      "slides": [
        {
          "title": "Barriers to Effective Interventions",
          "points": [
            "Limited access to resources",
            "Lack of trained professionals",
            "Cultural differences in approaches",
            "Stigma associated with disorders"
          ],
          "codes": [],
          "detail": "",
          "enriched_points": ""
        },
        {
          "title": "Research Gaps in Lower Middle-Income Countries",
          "points": [
            "Limited studies on interventions",
            "Need for culturally relevant practices",
            "Disparities in access to care",
            "Importance of local research initiatives"
          ],
          "codes": [],
          "detail": "",
          "enriched_points": ""
        },
        {
          "title": "Implementation Challenges",
          "points": [
            "Variability in intervention quality",
            "Need for ongoing training",
            "Collaboration among stakeholders",
            "Sustainability of programs"
          ],
          "codes": [],
          "detail": "",
          "enriched_points": ""
        }
      ]
    },
    {
      "name": "Innovative Solutions",
      "allocated_slides": 4,
      "slides": [
        {
          "title": "Emerging Intervention Strategies",
          "points": [
            "Telehealth and remote support",
            "Technology-assisted learning tools",
            "Parent-mediated interventions",
            "Community-based programs",
            "Innovative research findings"
          ],
          "codes": [],
          "detail": "",
          "enriched_points": ""
        },
        {
          "title": "Culturally Relevant Practices",
          "points": [
            "Adapting interventions to local contexts",
            "Involving families in the process",
            "Understanding cultural perceptions of disorders",
            "Building trust within communities"
          ],
          "codes": [],
          "detail": "",
          "enriched_points": ""
        },
        {
          "title": "Collaboration and Partnerships",
          "points": [
            "Engaging healthcare providers",
            "Involving educators and schools",
            "Strengthening family support networks",
            "Creating multidisciplinary teams"
          ],
          "codes": [],
          "detail": "",
          "enriched_points": ""
        },
        {
          "title": "Advocacy for Policy Changes",
          "points": [
            "Importance of funding for research",
            "Advocating for inclusive education",
            "Promoting awareness and understanding",
            "Supporting families and caregivers"
          ],
          "codes": [],
          "detail": "",
          "enriched_points": ""
        }
      ]
    },
    {
      "name": "Case Studies",
      "allocated_slides": 2,
      "slides": [
        {
          "title": "Successful Intervention Case Study 1",
          "points": [
            "Overview of the case",
            "Intervention strategies used",
            "Outcomes achieved",
            "Lessons learned"
          ],
          "codes": [],
          "detail": "",
          "enriched_points": ""
        },
        {
          "title": "Successful Intervention Case Study 2",
          "points": [
            "Overview of the case",
            "Intervention strategies used",
            "Outcomes achieved",
            "Lessons learned"
          ],
          "codes": [],
          "detail": "",
          "enriched_points": ""
        }
      ]
    },
    {
      "name": "Future Directions",
      "allocated_slides": 2,
      "slides": [
        {
          "title": "Research Priorities",
          "points": [
            "Focus on lower middle-income countries",
            "Developing culturally relevant interventions",
            "Longitudinal studies on outcomes",
            "Collaboration with local researchers"
          ],
          "codes": [],
          "detail": "",
          "enriched_points": ""
        },
        {
          "title": "Conclusion and Call to Action",
          "points": [
            "Importance of early intervention",
            "Need for comprehensive support",
            "Encouraging collaboration among stakeholders",
            "Advocating for continued research and funding"
          ],
          "codes": [],
          "detail": "",
          "enriched_points": ""
        }
      ]
    }
  ]
}