{
  "recommended_slides": 22,
  "section_distribution": {
    "Introduction": 3,
    "Situation": 4,
    "Complication": 4,
    "Question": 3,
    "Answer": 4,
    "Case Studies": 2,
    "Implications for Policy": 2
  },
  "ppt_outline": [
    {
      "name": "Introduction",
      "allocated_slides": 3,
      "slides": [
        {
          "title": "Understanding Behavioral Insights",
          "points": [
            "Definition of behavioral insights",
            "Interdisciplinary approach",
            "Importance in policy-making",
            "Key contributors to the field",
            "Real-world applications"
          ],
          "codes": [],
          "detail": "",
          "enriched_points": ""
        },
        {
          "title": "The Role of Behavioral Insights in Policy",
          "points": [
            "Transformative approach",
            "Influencing human behavior",
            "Addressing societal challenges",
            "Empirical research foundation"
          ],
          "codes": [],
          "detail": "",
          "enriched_points": ""
        },
        {
          "title": "Overview of the Presentation",
          "points": [
            "Key topics to be covered",
            "Structure of the presentation",
            "Importance of ethical considerations"
          ],
          "codes": [],
          "detail": "",
          "enriched_points": ""
        }
      ]
    },
    {
      "name": "Situation",
      "allocated_slides": 4,
      "slides": [
        {
          "title": "Current State of Policy-Making",
          "points": [
            "Traditional models of decision-making",
            "Assumptions of rationality",
            "Limitations of existing policies",
            "Need for innovative approaches"
          ],
          "codes": [],
          "detail": "",
          "enriched_points": ""
        },
        {
          "title": "Emergence of Behavioral Insights",
          "points": [
            "Historical context",
            "Influence of psychology and economics",
            "Rise of the Behavioral Insights Team",
            "Global recognition of BIs"
          ],
          "codes": [],
          "detail": "",
          "enriched_points": ""
        },
        {
          "title": "Understanding Human Behavior",
          "points": [
            "Cognitive biases and heuristics",
            "Impact of social factors",
            "Emotional influences on decisions",
            "Examples of irrational behavior"
          ],
          "codes": [],
          "detail": "",
          "enriched_points": ""
        },
        {
          "title": "Importance of Nudging",
          "points": [
            "Definition of nudging",
            "How nudges work",
            "Examples of successful nudges",
            "Benefits of nudging in policy"
          ],
          "codes": [],
          "detail": "",
          "enriched_points": ""
        }
      ]
    },
    {
      "name": "Complication",
      "allocated_slides": 4,
      "slides": [
        {
          "title": "Challenges in Implementing Behavioral Insights",
          "points": [
            "Overreliance on RCTs",
            "Generalizability issues",
            "Local context considerations",
            "Complexity of human behavior"
          ],
          "codes": [],
          "detail": "",
          "enriched_points": ""
        },
        {
          "title": "Ethical Concerns",
          "points": [
            "Autonomy vs. manipulation",
            "Consent in nudging",
            "Potential for misuse",
            "Balancing effectiveness and ethics"
          ],
          "codes": [],
          "detail": "",
          "enriched_points": ""
        },
        {
          "title": "Bounded Rationality of Policymakers",
          "points": [
            "Simplistic models of behavior",
            "Risk of oversimplification",
            "Need for nuanced understanding",
            "Training and education for policymakers"
          ],
          "codes": [],
          "detail": "",
          "enriched_points": ""
        },
        {
          "title": "Resistance to Change",
          "points": [
            "Institutional inertia",
            "Cultural barriers",
            "Skepticism towards behavioral approaches",
            "Need for advocacy and education"
          ],
          "codes": [],
          "detail": "",
          "enriched_points": ""
        }
      ]
    },
    {
      "name": "Question",
      "allocated_slides": 3,
      "slides": [
        {
          "title": "Key Questions for Policymakers",
          "points": [
            "How to effectively integrate BIs?",
            "What ethical frameworks should guide interventions?",
            "How to measure success of behavioral interventions?"
          ],
          "codes": [],
          "detail": "",
          "enriched_points": ""
        },
        {
          "title": "Addressing Ethical Dilemmas",
          "points": [
            "What constitutes ethical nudging?",
            "How to ensure transparency?",
            "How to involve stakeholders in decision-making?"
          ],
          "codes": [],
          "detail": "",
          "enriched_points": ""
        },
        {
          "title": "Future Directions for Research",
          "points": [
            "What gaps exist in current research?",
            "How to adapt BIs to different contexts?",
            "What role will technology play in future interventions?"
          ],
          "codes": [],
          "detail": "",
          "enriched_points": ""
        }
      ]
    },
    {
      "name": "Answer",
      "allocated_slides": 4,
      "slides": [
        {
          "title": "Effective Integration of Behavioral Insights",
          "points": [
            "Utilizing frameworks like EAST",
            "Collaborating with behavioral scientists",
            "Incorporating local context",
            "Continuous evaluation and adaptation"
          ],
          "codes": [],
          "detail": "",
          "enriched_points": ""
        },
        {
          "title": "Ethical Guidelines for Policymakers",
          "points": [
            "Establishing clear ethical standards",
            "Ensuring informed consent",
            "Promoting transparency in interventions",
            "Engaging with the public"
          ],
          "codes": [],
          "detail": "",
          "enriched_points": ""
        },
        {
          "title": "Measuring Success of Interventions",
          "points": [
            "Defining success metrics",
            "Using qualitative and quantitative data",
            "Feedback loops for improvement",
            "Case studies of successful interventions"
          ],
          "codes": [],
          "detail": "",
          "enriched_points": ""
        },
        {
          "title": "Adapting to Future Challenges",
          "points": [
            "Embracing technological advancements",
            "Staying informed on behavioral research",
            "Flexibility in policy design",
            "Building a culture of innovation"
          ],
          "codes": [],
          "detail": "",
          "enriched_points": ""
        }
      ]
    },
    {
      "name": "Case Studies",
      "allocated_slides": 2,
      "slides": [
        {
          "title": "Successful Case Study: Organ Donation",
          "points": [
            "Opt-out system implementation",
            "Increase in donor rates",
            "Behavioral insights applied",
            "Lessons learned"
          ],
          "codes": [],
          "detail": "",
          "enriched_points": ""
        },
        {
          "title": "Case Study: Tax Compliance",
          "points": [
            "Nudges to improve compliance",
            "Behavioral messaging strategies",
            "Impact assessment",
            "Scalability of interventions"
          ],
          "codes": [],
          "detail": "",
          "enriched_points": ""
        }
      ]
    },
    {
      "name": "Implications for Policy",
      "allocated_slides": 2,
      "slides": [
        {
          "title": "Transformative Potential of Behavioral Insights",
          "points": [
            "Enhancing policy effectiveness",
            "Addressing complex societal issues",
            "Promoting individual well-being",
            "Fostering public trust"
          ],
          "codes": [],
          "detail": "",
          "enriched_points": ""
        },
        {
          "title": "Future of Behavioral Insights in Policy",
          "points": [
            "Continued research and development",
            "Integration into mainstream policy-making",
            "Collaboration across disciplines",
            "Commitment to ethical practices"
          ],
          "codes": [],
          "detail": "",
          "enriched_points": ""
        }
      ]
    }
  ]
}