{
  "recommended_slides": 22,
  "section_distribution": {
    "Introduction": 3,
    "Background": 2,
    "Methodology": 4,
    "Data Sources": 3,
    "Analysis Techniques": 3,
    "Results": 4,
    "Discussion": 2,
    "Implications": 1
  },
  "ppt_outline": [
    {
      "name": "Introduction",
      "allocated_slides": 3,
      "slides": [
        {
          "title": "Overview of Remote Sensing",
          "points": [
            "Definition of remote sensing",
            "Importance in agriculture",
            "Technological advancements"
          ],
          "codes": [],
          "detail": "",
          "enriched_points": ""
        },
        {
          "title": "Purpose of the Report",
          "points": [
            "Explore applications",
            "Analyze benefits and limitations",
            "Discuss future trends"
          ],
          "codes": [],
          "detail": "",
          "enriched_points": ""
        },
        {
          "title": "Significance of Yield Forecasting",
          "points": [
            "Impact on food security",
            "Role in sustainable farming",
            "Need for accurate predictions"
          ],
          "codes": [],
          "detail": "",
          "enriched_points": ""
        }
      ]
    },
    {
      "name": "Background",
      "allocated_slides": 2,
      "slides": [
        {
          "title": "Types of Remote Sensing Technologies",
          "points": [
            "Satellite sensors",
            "Drone-based sensors",
            "Ground-based sensors"
          ],
          "codes": [],
          "detail": "",
          "enriched_points": ""
        },
        {
          "title": "Historical Context",
          "points": [
            "Evolution of remote sensing",
            "Early applications in agriculture"
          ],
          "codes": [],
          "detail": "",
          "enriched_points": ""
        }
      ]
    },
    {
      "name": "Methodology",
      "allocated_slides": 4,
      "slides": [
        {
          "title": "Data Collection Methods",
          "points": [
            "Satellite imagery",
            "Drone surveillance",
            "Ground sensor data",
            "Integration of data sources"
          ],
          "codes": [],
          "detail": "",
          "enriched_points": ""
        },
        {
          "title": "Data Processing Techniques",
          "points": [
            "Image analysis",
            "Machine learning algorithms",
            "Data assimilation methods"
          ],
          "codes": [],
          "detail": "",
          "enriched_points": ""
        },
        {
          "title": "Modeling Approaches",
          "points": [
            "Vegetation indices",
            "Crop growth models",
            "Statistical methods"
          ],
          "codes": [],
          "detail": "",
          "enriched_points": ""
        },
        {
          "title": "Validation of Results",
          "points": [
            "Field trials",
            "Comparison with historical data",
            "Accuracy assessment"
          ],
          "codes": [],
          "detail": "",
          "enriched_points": ""
        }
      ]
    },
    {
      "name": "Data Sources",
      "allocated_slides": 3,
      "slides": [
        {
          "title": "Remote Sensing Platforms",
          "points": [
            "MODIS",
            "Sentinel-2",
            "Landsat"
          ],
          "codes": [],
          "detail": "",
          "enriched_points": ""
        },
        {
          "title": "Weather and Soil Data",
          "points": [
            "Importance of weather data",
            "Soil moisture and nutrient levels"
          ],
          "codes": [],
          "detail": "",
          "enriched_points": ""
        },
        {
          "title": "Integration of Multi-source Data",
          "points": [
            "Benefits of combining data",
            "Improving prediction accuracy"
          ],
          "codes": [],
          "detail": "",
          "enriched_points": ""
        }
      ]
    },
    {
      "name": "Analysis Techniques",
      "allocated_slides": 3,
      "slides": [
        {
          "title": "Machine Learning in Yield Forecasting",
          "points": [
            "Role of ML algorithms",
            "Case studies in cotton and sugarcane"
          ],
          "codes": [],
          "detail": "",
          "enriched_points": ""
        },
        {
          "title": "Use of Vegetation Indices",
          "points": [
            "NDVI and its applications",
            "Enhancing model accuracy"
          ],
          "codes": [],
          "detail": "",
          "enriched_points": ""
        },
        {
          "title": "Data Assimilation Techniques",
          "points": [
            "Ensemble Kalman Filter",
            "Real-time updates"
          ],
          "codes": [],
          "detail": "",
          "enriched_points": ""
        }
      ]
    },
    {
      "name": "Results",
      "allocated_slides": 4,
      "slides": [
        {
          "title": "Key Findings from Remote Sensing",
          "points": [
            "Improved yield predictions",
            "Enhanced crop health assessments",
            "Resource management insights"
          ],
          "codes": [],
          "detail": "",
          "enriched_points": ""
        },
        {
          "title": "Comparative Analysis",
          "points": [
            "Remote sensing vs. traditional methods",
            "Accuracy improvements"
          ],
          "codes": [],
          "detail": "",
          "enriched_points": ""
        },
        {
          "title": "Case Study Results",
          "points": [
            "Successful applications in various crops",
            "Impact on decision-making"
          ],
          "codes": [],
          "detail": "",
          "enriched_points": ""
        },
        {
          "title": "Statistical Outcomes",
          "points": [
            "Reduction in RMSE",
            "Increased prediction reliability"
          ],
          "codes": [],
          "detail": "",
          "enriched_points": ""
        }
      ]
    },
    {
      "name": "Discussion",
      "allocated_slides": 2,
      "slides": [
        {
          "title": "Challenges in Remote Sensing",
          "points": [
            "Environmental factors affecting data",
            "Complexity of data processing"
          ],
          "codes": [],
          "detail": "",
          "enriched_points": ""
        },
        {
          "title": "Future Directions",
          "points": [
            "Emerging technologies",
            "Potential for further integration"
          ],
          "codes": [],
          "detail": "",
          "enriched_points": ""
        }
      ]
    },
    {
      "name": "Implications",
      "allocated_slides": 1,
      "slides": [
        {
          "title": "Conclusion and Recommendations",
          "points": [
            "Importance of remote sensing in agriculture",
            "Need for continued research",
            "Support for sustainable practices"
          ],
          "codes": [],
          "detail": "",
          "enriched_points": ""
        }
      ]
    }
  ]
}