{
  "recommended_slides": 22,
  "section_distribution": {
    "Introduction": 3,
    "Situation": 4,
    "Complication": 4,
    "Question": 3,
    "Answer": 6,
    "Case Studies": 2
  },
  "ppt_outline": [
    {
      "name": "Introduction",
      "allocated_slides": 3,
      "slides": [
        {
          "title": "Understanding Behavioral Economics",
          "points": [
            "Definition of behavioral economics",
            "Combination of psychology and economics",
            "Importance in consumer decision-making",
            "Key figures: Kahneman and Tversky"
          ],
          "codes": [],
          "detail": "",
          "enriched_points": ""
        },
        {
          "title": "Relevance to Marketing",
          "points": [
            "Influence on marketing strategies",
            "Understanding consumer behavior",
            "Enhancing campaign effectiveness",
            "Addressing cognitive biases"
          ],
          "codes": [],
          "detail": "",
          "enriched_points": ""
        },
        {
          "title": "Overview of Key Principles",
          "points": [
            "Loss aversion",
            "Anchoring",
            "Social proof",
            "Scarcity",
            "Framing effects"
          ],
          "codes": [],
          "detail": "",
          "enriched_points": ""
        }
      ]
    },
    {
      "name": "Situation",
      "allocated_slides": 4,
      "slides": [
        {
          "title": "Current Marketing Landscape",
          "points": [
            "Highly competitive market",
            "Need for effective strategies",
            "Consumer behavior complexity",
            "Importance of psychological insights"
          ],
          "codes": [],
          "detail": "",
          "enriched_points": ""
        },
        {
          "title": "Traditional vs. Behavioral Economics",
          "points": [
            "Rational vs. irrational decision-making",
            "Cognitive biases in consumer choices",
            "Limitations of traditional models",
            "Emergence of behavioral insights"
          ],
          "codes": [],
          "detail": "",
          "enriched_points": ""
        },
        {
          "title": "Consumer Decision-Making Process",
          "points": [
            "Stages of decision-making",
            "Influence of emotions",
            "Role of social factors",
            "Impact of cognitive shortcuts"
          ],
          "codes": [],
          "detail": "",
          "enriched_points": ""
        },
        {
          "title": "Challenges in Marketing",
          "points": [
            "Understanding diverse consumer motivations",
            "Adapting to changing behaviors",
            "Avoiding ineffective strategies",
            "Need for ethical considerations"
          ],
          "codes": [],
          "detail": "",
          "enriched_points": ""
        }
      ]
    },
    {
      "name": "Complication",
      "allocated_slides": 4,
      "slides": [
        {
          "title": "Cognitive Biases in Marketing",
          "points": [
            "Loss aversion leading to missed opportunities",
            "Anchoring affecting price perception",
            "Social proof creating herd behavior",
            "Scarcity leading to impulsive decisions"
          ],
          "codes": [],
          "detail": "",
          "enriched_points": ""
        },
        {
          "title": "Ethical Dilemmas",
          "points": [
            "Manipulation vs. persuasion",
            "Consumer autonomy concerns",
            "Long-term trust vs. short-term gains",
            "Balancing effectiveness with ethics"
          ],
          "codes": [],
          "detail": "",
          "enriched_points": ""
        },
        {
          "title": "Consumer Trust Issues",
          "points": [
            "Impact of unethical practices",
            "Erosion of brand loyalty",
            "Importance of transparency",
            "Building long-term relationships"
          ],
          "codes": [],
          "detail": "",
          "enriched_points": ""
        },
        {
          "title": "Market Saturation",
          "points": [
            "Overwhelming choices for consumers",
            "Difficulty in standing out",
            "Need for innovative approaches",
            "Challenges in capturing attention"
          ],
          "codes": [],
          "detail": "",
          "enriched_points": ""
        }
      ]
    },
    {
      "name": "Question",
      "allocated_slides": 3,
      "slides": [
        {
          "title": "How Can Marketers Leverage Behavioral Insights?",
          "points": [
            "Understanding key principles",
            "Applying insights ethically",
            "Creating effective campaigns",
            "Building consumer trust"
          ],
          "codes": [],
          "detail": "",
          "enriched_points": ""
        },
        {
          "title": "What Are the Risks of Misusing Behavioral Economics?",
          "points": [
            "Potential for manipulation",
            "Loss of consumer trust",
            "Legal implications",
            "Long-term brand damage"
          ],
          "codes": [],
          "detail": "",
          "enriched_points": ""
        },
        {
          "title": "How to Balance Effectiveness and Ethics?",
          "points": [
            "Prioritizing consumer welfare",
            "Transparent marketing practices",
            "Fostering long-term relationships",
            "Adhering to ethical guidelines"
          ],
          "codes": [],
          "detail": "",
          "enriched_points": ""
        }
      ]
    },
    {
      "name": "Answer",
      "allocated_slides": 6,
      "slides": [
        {
          "title": "Key Principles of Behavioral Economics",
          "points": [
            "Loss aversion: avoiding losses",
            "Anchoring: initial information impact",
            "Social proof: influence of others",
            "Scarcity: urgency in purchasing",
            "Framing: presentation of information"
          ],
          "codes": [],
          "detail": "",
          "enriched_points": ""
        },
        {
          "title": "Practical Applications in Marketing",
          "points": [
            "Limited-time offers",
            "Discount displays",
            "Testimonials and reviews",
            "Highlighting low stock",
            "Choice architecture"
          ],
          "codes": [],
          "detail": "",
          "enriched_points": ""
        },
        {
          "title": "Case Study: Successful Campaigns",
          "points": [
            "Example of loss aversion in action",
            "Use of social proof in marketing",
            "Scarcity tactics in retail",
            "Anchoring in pricing strategies",
            "Ethical considerations in campaigns"
          ],
          "codes": [],
          "detail": "",
          "enriched_points": ""
        },
        {
          "title": "Strategies for Ethical Marketing",
          "points": [
            "Transparency in messaging",
            "Respecting consumer choices",
            "Avoiding manipulative tactics",
            "Building trust through honesty",
            "Long-term relationship focus"
          ],
          "codes": [],
          "detail": "",
          "enriched_points": ""
        },
        {
          "title": "Future Trends in Behavioral Marketing",
          "points": [
            "Increased focus on ethics",
            "Integration of technology",
            "Personalization based on insights",
            "Emerging consumer behaviors",
            "Adapting to market changes"
          ],
          "codes": [],
          "detail": "",
          "enriched_points": ""
        },
        {
          "title": "Conclusion and Key Takeaways",
          "points": [
            "Behavioral economics enhances marketing",
            "Ethical considerations are crucial",
            "Understanding consumer behavior is key",
            "Effective strategies drive engagement",
            "Long-term trust fosters loyalty"
          ],
          "codes": [],
          "detail": "",
          "enriched_points": ""
        }
      ]
    },
    {
      "name": "Case Studies",
      "allocated_slides": 2,
      "slides": [
        {
          "title": "Case Study 1: Successful Use of Loss Aversion",
          "points": [
            "Campaign overview",
            "Application of loss aversion",
            "Results achieved",
            "Consumer response",
            "Lessons learned"
          ],
          "codes": [],
          "detail": "",
          "enriched_points": ""
        },
        {
          "title": "Case Study 2: Ethical Marketing Practices",
          "points": [
            "Company overview",
            "Strategies employed",
            "Impact on consumer trust",
            "Long-term benefits",
            "Key takeaways"
          ],
          "codes": [],
          "detail": "",
          "enriched_points": ""
        }
      ]
    }
  ]
}