{
  "recommended_slides": 22,
  "section_distribution": {
    "Introduction": 3,
    "Background on Nano-innovation": 3,
    "Intellectual Property Overview": 3,
    "Types of Intellectual Property in Nano-innovation": 4,
    "Challenges in Protecting IP in Nano-innovation": 3,
    "Case Studies": 3,
    "Future Trends in IP and Nano-innovation": 2,
    "Recommendations for Stakeholders": 2
  },
  "ppt_outline": [
    {
      "name": "Introduction",
      "allocated_slides": 3,
      "slides": [
        {
          "title": "Overview of Nano-innovation",
          "points": [
            "Definition of nanotechnology",
            "Importance in various industries",
            "Current trends in nano-innovation",
            "Impact on society",
            "Role of intellectual property"
          ],
          "codes": [],
          "detail": "",
          "enriched_points": ""
        },
        {
          "title": "Purpose of the Report",
          "points": [
            "To explore IP in nano-innovation",
            "Identify challenges in patenting",
            "Examine trends in patent filings",
            "Highlight ethical considerations",
            "Provide recommendations for stakeholders"
          ],
          "codes": [],
          "detail": "",
          "enriched_points": ""
        },
        {
          "title": "Structure of the Presentation",
          "points": [
            "Introduction",
            "Background on Nano-innovation",
            "IP Overview",
            "Challenges in Protecting IP",
            "Future Trends",
            "Recommendations"
          ],
          "codes": [],
          "detail": "",
          "enriched_points": ""
        }
      ]
    },
    {
      "name": "Background on Nano-innovation",
      "allocated_slides": 3,
      "slides": [
        {
          "title": "History of Nanotechnology",
          "points": [
            "Origins of nanotechnology",
            "Key milestones in development",
            "Evolution of applications",
            "Significant breakthroughs",
            "Current state of research"
          ],
          "codes": [],
          "detail": "",
          "enriched_points": ""
        },
        {
          "title": "Applications of Nanotechnology",
          "points": [
            "Medicine and healthcare",
            "Electronics and materials",
            "Environmental applications",
            "Energy solutions",
            "Consumer products"
          ],
          "codes": [],
          "detail": "",
          "enriched_points": ""
        },
        {
          "title": "Market Dynamics",
          "points": [
            "Growth of the nanotechnology market",
            "Investment trends",
            "Competitive landscape",
            "Global players",
            "Future market predictions"
          ],
          "codes": [],
          "detail": "",
          "enriched_points": ""
        }
      ]
    },
    {
      "name": "Intellectual Property Overview",
      "allocated_slides": 3,
      "slides": [
        {
          "title": "What is Intellectual Property?",
          "points": [
            "Definition of IP",
            "Types of IP rights",
            "Importance of IP in innovation",
            "IP as a competitive advantage",
            "IP management strategies"
          ],
          "codes": [],
          "detail": "",
          "enriched_points": ""
        },
        {
          "title": "Role of IP in Nano-innovation",
          "points": [
            "Protection of innovations",
            "Encouragement of investment",
            "Facilitation of commercialization",
            "Fostering competition",
            "Balancing public interest"
          ],
          "codes": [],
          "detail": "",
          "enriched_points": ""
        },
        {
          "title": "Key IP Rights in Nanotechnology",
          "points": [
            "Patents",
            "Trade secrets",
            "Trademarks",
            "Copyrights",
            "Design rights"
          ],
          "codes": [],
          "detail": "",
          "enriched_points": ""
        }
      ]
    },
    {
      "name": "Types of Intellectual Property in Nano-innovation",
      "allocated_slides": 4,
      "slides": [
        {
          "title": "Patents",
          "points": [
            "Definition and purpose",
            "Types of patents (utility, design)",
            "Importance in nanotechnology",
            "Challenges in patenting",
            "Case examples"
          ],
          "codes": [],
          "detail": "",
          "enriched_points": ""
        },
        {
          "title": "Trade Secrets",
          "points": [
            "Definition and significance",
            "Examples in nanotechnology",
            "Advantages over patents",
            "Risks and challenges",
            "Best practices for protection"
          ],
          "codes": [],
          "detail": "",
          "enriched_points": ""
        },
        {
          "title": "Trademarks",
          "points": [
            "Role in branding",
            "Importance for market recognition",
            "Examples in nano-products",
            "Legal considerations",
            "Impact on consumer trust"
          ],
          "codes": [],
          "detail": "",
          "enriched_points": ""
        },
        {
          "title": "Copyrights and Design Rights",
          "points": [
            "Overview of copyrights",
            "Importance in creative works",
            "Design rights in nanotechnology",
            "Examples and case studies",
            "Legal implications"
          ],
          "codes": [],
          "detail": "",
          "enriched_points": ""
        }
      ]
    },
    {
      "name": "Challenges in Protecting IP in Nano-innovation",
      "allocated_slides": 3,
      "slides": [
        {
          "title": "Interdisciplinary Nature of Nanotechnology",
          "points": [
            "Complexity of innovations",
            "Difficulty in establishing novelty",
            "Non-obviousness criteria",
            "Impact on patentability",
            "Examples of interdisciplinary challenges"
          ],
          "codes": [],
          "detail": "",
          "enriched_points": ""
        },
        {
          "title": "Patent Thickets",
          "points": [
            "Definition and implications",
            "Overlapping patents in nanotechnology",
            "Barriers to entry for new innovators",
            "Strategies to navigate thickets",
            "Case studies"
          ],
          "codes": [],
          "detail": "",
          "enriched_points": ""
        },
        {
          "title": "Global Patent Landscape",
          "points": [
            "Territorial nature of patents",
            "Variability in patent laws",
            "Challenges in international filings",
            "Impact on global competition",
            "Strategies for global IP management"
          ],
          "codes": [],
          "detail": "",
          "enriched_points": ""
        }
      ]
    },
    {
      "name": "Case Studies",
      "allocated_slides": 3,
      "slides": [
        {
          "title": "Successful Nano-innovations",
          "points": [
            "Overview of notable innovations",
            "IP strategies employed",
            "Market impact",
            "Lessons learned",
            "Future potential"
          ],
          "codes": [],
          "detail": "",
          "enriched_points": ""
        },
        {
          "title": "Challenges Faced by Innovators",
          "points": [
            "Case examples of failed patents",
            "Impact of patent thickets",
            "Legal disputes",
            "Lessons learned",
            "Recommendations for future innovators"
          ],
          "codes": [],
          "detail": "",
          "enriched_points": ""
        },
        {
          "title": "Comparative Analysis of Countries",
          "points": [
            "Patent filing trends in the U.S. vs. China",
            "Impact on global competition",
            "Case studies of successful countries",
            "Lessons for other nations",
            "Future outlook"
          ],
          "codes": [],
          "detail": "",
          "enriched_points": ""
        }
      ]
    },
    {
      "name": "Future Trends in IP and Nano-innovation",
      "allocated_slides": 2,
      "slides": [
        {
          "title": "Emerging Trends in Patenting",
          "points": [
            "Increased patent filings",
            "Geographical shifts in innovation",
            "Focus on sustainability",
            "Collaboration among nations",
            "Impact of AI on patenting"
          ],
          "codes": [],
          "detail": "",
          "enriched_points": ""
        },
        {
          "title": "The Role of Ethics in IP Management",
          "points": [
            "Importance of ethical considerations",
            "Public perception of nanotechnology",
            "Balancing innovation and ethics",
            "Engaging stakeholders",
            "Future implications"
          ],
          "codes": [],
          "detail": "",
          "enriched_points": ""
        }
      ]
    },
    {
      "name": "Recommendations for Stakeholders",
      "allocated_slides": 2,
      "slides": [
        {
          "title": "Strategies for Effective IP Management",
          "points": [
            "Develop comprehensive IP strategies",
            "Engage in collaborative research",
            "Monitor patent landscape",
            "Educate stakeholders",
            "Foster innovation ecosystems"
          ],
          "codes": [],
          "detail": "",
          "enriched_points": ""
        },
        {
          "title": "Addressing Ethical Considerations",
          "points": [
            "Promote public awareness",
            "Incorporate ethical frameworks",
            "Engage in open dialogues",
            "Evaluate environmental impacts",
            "Ensure equitable access"
          ],
          "codes": [],
          "detail": "",
          "enriched_points": ""
        }
      ]
    }
  ]
}